hiddenpoem/.gitignore
hiddenpoem/README.md
hiddenpoem/__init__.py
hiddenpoem/app.py
hiddenpoem/app_run.py
hiddenpoem/gun.py
hiddenpoem/gun_run.sh
hiddenpoem/requirements.txt
hiddenpoem/data_cache/__init__.py
hiddenpoem/data_cache/cangtoushi5.txt
hiddenpoem/data_cache/cangtoushi7.txt
hiddenpoem/data_cache/poem_ext.txt
hiddenpoem/log_cache/__init__.py
hiddenpoem/log_cache/access.log
hiddenpoem/log_cache/error.log
hiddenpoem/log_cache/gunicorn.pid
HiddenPoem-2021.1.15.18.18.47.dist-info/METADATA
HiddenPoem-2021.1.15.18.18.47.dist-info/WHEEL
HiddenPoem-2021.1.15.18.18.47.dist-info/entry_points.txt
HiddenPoem-2021.1.15.18.18.47.dist-info/top_level.txt
HiddenPoem-2021.1.15.18.18.47.dist-info/RECORD
