Metadata-Version: 2.1
Name: HiddenPoem
Version: 2021.1.15.18.18.47
Summary: description
Home-page: https://github.com/Jie-Yuan/HiddenPoem
Author: YuanJie
Author-email: 313303303@qq.com
Maintainer: JieYuan
Maintainer-email: 313303303@qq.com
License: Apache
Keywords: tool wheel,yuanjie,utils
Platform: all
Classifier: Operating System :: OS Independent
Classifier: Intended Audience :: Developers
Classifier: License :: OSI Approved :: MIT License
Classifier: Programming Language :: Python
Classifier: Programming Language :: Python :: Implementation
Requires-Dist: meutils
